junklang/__init__.py
junklang/cli.py
junklang/interpreter.py
junklang-0.1.1.dist-info/licenses/LICENSE
junklang-0.1.1.dist-info/METADATA
junklang-0.1.1.dist-info/WHEEL
junklang-0.1.1.dist-info/entry_points.txt
junklang-0.1.1.dist-info/top_level.txt
junklang-0.1.1.dist-info/RECORD
