Metadata-Version: 2.4
Name: junklang
Version: 0.1.1
Summary: Interpreter for the JunkLang esolang
Author: Abhay Gupta
Author-email: Abhay Gupta <abhaygupta.hsj@email.com>
License: MIT
Requires-Python: >=3.6
License-File: LICENSE
Dynamic: author
Dynamic: license-file
Dynamic: requires-python
